rtl/fifo.sv
module fifo_sync # (
    parameter DATA_WIDTH = 8,
    parameter DEPTH      = 16
)(
    input logic CLK,
    input logic RST_N,

    // Write Domain
    input logic WR_EN,
    input logic [DATA_WIDTH-1:0] WR_DATA,
    output logic FULL,

    // Read Domain
    input logic RD_EN,
    output logic [DATA_WIDTH-1:0] RD_DATA,
    output logic EMPTY
);

    localparam ADDR_WIDTH = $clog2(DEPTH);

    logic [DATA_WIDTH-1:0] mem [0:DEPTH-1];

    logic [ADDR_WIDTH:0] wr_ptr;
    logic [ADDR_WIDTH:0] rd_ptr;

    // Write Data to FIFO
    always_ff @(posedge CLK) begin
        if(!RST_N) begin
            wr_ptr <= 0; 
        end else if(WR_EN && !FULL) begin
            mem[wr_ptr[ADDR_WIDTH-1:0]] <= WR_DATA;
            wr_ptr <= wr_ptr + 1;
        end
    end

    // Read Data from FIFO
    always_ff @(posedge CLK) begin
        if(!RST_N) begin
            rd_ptr <= 0; 
            RD_DATA <= 0;
        end else if(RD_EN && !EMPTY) begin
            RD_DATA <= mem[rd_ptr[ADDR_WIDTH-1:0]];
            rd_ptr <= rd_ptr + 1;
        end
    end

    // Assign Full and Empty Flags
    assign FULL =
    (wr_ptr[ADDR_WIDTH] != rd_ptr[ADDR_WIDTH]) &&
    (wr_ptr[ADDR_WIDTH-1:0] == rd_ptr[ADDR_WIDTH-1:0]);

    assign EMPTY = (wr_ptr == rd_ptr);
endmodule

tb/tb_fifo.sv
module tb_fifo # (
    parameter DATA_WIDTH = 8,
    parameter DEPTH      = 16
)();
    reg clk;
    reg rst_n;

    reg wr_en;
    reg [DATA_WIDTH-1:0] wr_data;
    wire full;

    reg rd_en;
    wire [DATA_WIDTH-1:0] rd_data;
    wire empty;

    initial begin 
        clk = 0;
        forever #5 clk = ~clk;
    end

    initial begin
        // Initialise and Test Reset
        rst_n = 0;
        wr_en = 0;
        rd_en = 0;

        wr_data = 0;

        #10;
        rst_n = 1;
        #5;

        // Test Single Write + Read Out
        wr_en = 1;
        wr_data = 5;

        #5;
        wr_en = 0;
        // Enable Read
        #5;
        rd_en = 1;
        #10;

        // Disable Read and Fill to Full
        rd_en = 0;
        wr_en = 1;
        wr_data = 5;
        #160;

        // Disable Write and Empty
        wr_en = 0;
        rd_en = 1;
        #150;

        // Test wr_ptr wraparound
        #5;
        rd_en = 0;
        wr_en = 1;
        #150;

        // Test wr_ptr wraparound
        #5;
        wr_en = 0;
        rd_en = 1;
        #140;

        #5;
        wr_en = 1;
        wr_data = 7;
        #20;

        
        #5;
        $finish;
    end

    fifo_sync uut (
        .CLK(clk),
        .RST_N(rst_n),
        .WR_EN(wr_en),
        .WR_DATA(wr_data),
        .FULL(full),
        .RD_EN(rd_en),
        .RD_DATA(rd_data),
        .EMPTY(empty)
    );
    
    initial begin
        $dumpfile("dump.vcd");
        $dumpvars(0, tb_fifo);
    end

endmodule

dump.vcd
$date
	Fri Jul 31 12:51:14 2026
$end
$version
	Icarus Verilog
$end
$timescale
	1s
$end
$scope module tb_fifo $end
$var wire 8 ! rd_data [7:0] $end
$var wire 1 " full $end
$var wire 1 # empty $end
$var parameter 32 $ DATA_WIDTH $end
$var parameter 32 % DEPTH $end
$var reg 1 & clk $end
$var reg 1 ' rd_en $end
$var reg 1 ( rst_n $end
$var reg 8 ) wr_data [7:0] $end
$var reg 1 * wr_en $end
$scope module uut $end
$var wire 1 & CLK $end
$var wire 1 " FULL $end
$var wire 1 ' RD_EN $end
$var wire 1 ( RST_N $end
$var wire 8 + WR_DATA [7:0] $end
$var wire 1 * WR_EN $end
$var wire 1 # EMPTY $end
$var parameter 32 , ADDR_WIDTH $end
$var parameter 32 - DATA_WIDTH $end
$var parameter 32 . DEPTH $end
$var reg 8 / RD_DATA [7:0] $end
$var reg 5 0 rd_ptr [4:0] $end
$var reg 5 1 wr_ptr [4:0] $end
$upscope $end
$upscope $end
$enddefinitions $end
$comment Show the parameter values. $end
$dumpall
b10000 .
b1000 -
b100 ,
b10000 %
b1000 $
$end
#0
$dumpvars
bx 1
bx 0
bx /
b0 +
0*
b0 )
0(
0'
0&
x#
x"
bx !
$end
#5
0"
1#
b0 1
b0 !
b0 /
b0 0
1&
#10
0&
1(
#15
0#
b1 1
1&
b101 )
b101 +
1*
#20
0&
0*
#25
1#
b1 0
b101 !
b101 /
1&
1'
#30
0&
#35
0#
b10 1
1&
1*
0'
#40
0&
#45
b11 1
1&
#50
0&
#55
b100 1
1&
#60
0&
#65
b101 1
1&
#70
0&
#75
b110 1
1&
#80
0&
#85
b111 1
1&
#90
0&
#95
b1000 1
1&
#100
0&
#105
b1001 1
1&
#110
0&
#115
b1010 1
1&
#120
0&
#125
b1011 1
1&
#130
0&
#135
b1100 1
1&
#140
0&
#145
b1101 1
1&
#150
0&
#155
b1110 1
1&
#160
0&
#165
b1111 1
1&
#170
0&
#175
b10000 1
1&
#180
0&
#185
1"
b10001 1
1&
#190
0&
#195
0"
b10 0
1&
1'
0*
#200
0&
#205
b11 0
1&
#210
0&
#215
b100 0
1&
#220
0&
#225
b101 0
1&
#230
0&
#235
b110 0
1&
#240
0&
#245
b111 0
1&
#250
0&
#255
b1000 0
1&
#260
0&
#265
b1001 0
1&
#270
0&
#275
b1010 0
1&
#280
0&
#285
b1011 0
1&
#290
0&
#295
b1100 0
1&
#300
0&
#305
b1101 0
1&
#310
0&
#315
b1110 0
1&
#320
0&
#325
b1111 0
1&
#330
0&
#335
b10000 0
1&
#340
0&
#345
1#
b10001 0
1&
#350
0&
1*
0'
#355
0#
b10010 1
1&
#360
0&
#365
b10011 1
1&
#370
0&
#375
b10100 1
1&
#380
0&
#385
b10101 1
1&
#390
0&
#395
b10110 1
1&
#400
0&
#405
b10111 1
1&
#410
0&
#415
b11000 1
1&
#420
0&
#425
b11001 1
1&
#430
0&
#435
b11010 1
1&
#440
0&
#445
b11011 1
1&
#450
0&
#455
b11100 1
1&
#460
0&
#465
b11101 1
1&
#470
0&
#475
b11110 1
1&
#480
0&
#485
b11111 1
1&
#490
0&
#495
b0 1
1&
#500
0&
#505
b10010 0
1&
1'
0*
#510
0&
#515
b10011 0
1&
#520
0&
#525
b10100 0
1&
#530
0&
#535
b10101 0
1&
#540
0&
#545
b10110 0
1&
#550
0&
#555
b10111 0
1&
#560
0&
#565
b11000 0
1&
#570
0&
#575
b11001 0
1&
#580
0&
#585
b11010 0
1&
#590
0&
#595
b11011 0
1&
#600
0&
#605
b11100 0
1&
#610
0&
#615
b11101 0
1&
#620
0&
#625
b11110 0
1&
#630
0&
#635
b11111 0
1&
#640
0&
#645
0"
1#
b0 0
1&
#650
0&
b111 )
b111 +
1*
#655
0#
b1 1
1&
#660
0&
#665
b10 1
0#
b1 0
b111 !
b111 /
1&
#670
0&
#675
b10 0
b11 1
1&
